Workbook

Sheet Dashboard
A1: Futures Capital Template v0.1
A2: Capital management dashboard for backtest and live futures records.
A4: Metric | B4: Value | C4: Meaning
A5: Starting Equity | B5: =Settings!B7 | C5: Initial strategy capital
A6: Current Account Equity | B6: =LOOKUP(2,1/(Trades!N:N<>""),Trades!N:N) | C6: Latest equity after trades
A7: Actual Withdrawals | B7: =Settings!B8 | C7: Money removed from account
A8: Total Wealth | B8: =B6+B7 | C8: Account equity + actual withdrawals
A9: Internal Locked | B9: =Settings!B9 | C9: Recorded but not actually removed
A10: Total Trades | B10: =COUNTIF(Trades!L:L,"<>") | C10: Closed trades
A11: Win Rate | B11: =IF(B10=0,"",COUNTIF(Trades!Q:Q,"Win")/B10) | C11: Winning trades / total trades
A12: Gross Profit | B12: =SUMIF(Trades!L:L,">0",Trades!L:L) | C12: Sum of wins
A13: Gross Loss | B13: =ABS(SUMIF(Trades!L:L,"<0",Trades!L:L)) | C13: Absolute sum of losses
A14: Profit Factor | B14: =IF(B13=0,"",B12/B13) | C14: Gross profit / gross loss
A15: Max Drawdown | B15: =MIN(Trades!P:P) | C15: Largest equity drop from peak
A16: Absolute PnL | B16: =B8-B5 | C16: Total wealth - starting equity
A17: Return on Starting Equity | B17: =IF(B5=0,"",B16/B5) | C17: Absolute PnL / starting equity
A18: Water Per Lot | B18: =Settings!B6 | C18: Margin + drawdown water
A19: Estimated Lots | B19: =IF(B18=0,"",ROUNDDOWN(B6/B18,0)) | C19: Equity divided by water per lot

Sheet Settings
A1: Field | B1: Value | C1: Note
A2: Product | B2: Micro Futures | C2: Example only
A3: Point Value | B3: 10 | C3: Cash value per point
A4: Margin Per Lot | B4: 28900 | C4: Update when exchange margin changes
A5: Drawdown Water Points | B5: 1300 | C5: Risk buffer per lot
A6: Water Per Lot | B6: =B4+B5*B3 | C6: Margin + drawdown points * point value
A7: Starting Equity | B7: 170000 | C7: Initial strategy capital
A8: Actual Withdrawals | B8: =SUMIFS(Withdrawals!C:C,Withdrawals!D:D,"Actual") | C8: Money removed from account
A9: Internal Locked | B9: =SUMIFS(Withdrawals!C:C,Withdrawals!D:D,"Locked") | C9: Recorded but still inside account

Sheet Trades
A1: Trade ID | B1: Module | C1: Entry Date | D1: Exit Date | E1: Direction | F1: Lots | G1: Entry Price | H1: Exit Price | I1: Points | J1: Gross PnL | K1: Costs | L1: Net PnL | M1: Equity Before | N1: Equity After | O1: Equity Peak | P1: Drawdown | Q1: Win/Loss | R1: Note
A2: 1 | B2: DAY | C2: 2026-01-02 | D2: 2026-01-06 | E2: Long | F2: 1 | G2: 20000 | H2: 20650 | I2: =IF(OR(E2="",G2="",H2=""),"",IF(E2="Short",G2-H2,H2-G2)) | J2: =IF(I2="","",I2*F2*Settings!$B$3) | K2: 120 | L2: =IF(J2="","",J2-K2) | M2: =Settings!$B$7 | N2: =IF(L2="","",M2+L2) | O2: =IF(N2="","",MAX(Settings!$B$7,N$2:N2)) | P2: =IF(N2="","",N2-O2) | Q2: =IF(L2="","",IF(L2>0,"Win",IF(L2<0,"Loss","Flat"))) | R2: Sample trend trade
A3: 2 | B3: M15_NIGHT | C3: 2026-01-08 | D3: 2026-01-08 | E3: Long | F3: 1 | G3: 20700 | H3: 20480 | I3: =IF(OR(E3="",G3="",H3=""),"",IF(E3="Short",G3-H3,H3-G3)) | J3: =IF(I3="","",I3*F3*Settings!$B$3) | K3: 120 | L3: =IF(J3="","",J3-K3) | M3: =IF(C3="","",N2) | N3: =IF(L3="","",M3+L3) | O3: =IF(N3="","",MAX(Settings!$B$7,N$2:N3)) | P3: =IF(N3="","",N3-O3) | Q3: =IF(L3="","",IF(L3>0,"Win",IF(L3<0,"Loss","Flat"))) | R3: Sample false breakout
A4: 3 | B4: T1O | C4: 2026-01-10 | D4: 2026-01-10 | E4: Short | F4: 1 | G4: 20300 | H4: 20120 | I4: =IF(OR(E4="",G4="",H4=""),"",IF(E4="Short",G4-H4,H4-G4)) | J4: =IF(I4="","",I4*F4*Settings!$B$3) | K4: 120 | L4: =IF(J4="","",J4-K4) | M4: =IF(C4="","",N3) | N4: =IF(L4="","",M4+L4) | O4: =IF(N4="","",MAX(Settings!$B$7,N$2:N4)) | P4: =IF(N4="","",N4-O4) | Q4: =IF(L4="","",IF(L4>0,"Win",IF(L4<0,"Loss","Flat"))) | R4: Sample short plugin
A5: 4 | B5: M15_NIGHT | C5: 2026-01-15 | D5: 2026-01-15 | E5: Long | F5: 1 | G5: 20550 | H5: 20720 | I5: =IF(OR(E5="",G5="",H5=""),"",IF(E5="Short",G5-H5,H5-G5)) | J5: =IF(I5="","",I5*F5*Settings!$B$3) | K5: 120 | L5: =IF(J5="","",J5-K5) | M5: =IF(C5="","",N4) | N5: =IF(L5="","",M5+L5) | O5: =IF(N5="","",MAX(Settings!$B$7,N$2:N5)) | P5: =IF(N5="","",N5-O5) | Q5: =IF(L5="","",IF(L5>0,"Win",IF(L5<0,"Loss","Flat"))) | R5: Sample night trade
A6: 5 | B6: DAY | C6: 2026-01-20 | D6: 2026-01-24 | E6: Long | F6: 1 | G6: 20800 | H6: 19880 | I6: =IF(OR(E6="",G6="",H6=""),"",IF(E6="Short",G6-H6,H6-G6)) | J6: =IF(I6="","",I6*F6*Settings!$B$3) | K6: 120 | L6: =IF(J6="","",J6-K6) | M6: =IF(C6="","",N5) | N6: =IF(L6="","",M6+L6) | O6: =IF(N6="","",MAX(Settings!$B$7,N$2:N6)) | P6: =IF(N6="","",N6-O6) | Q6: =IF(L6="","",IF(L6>0,"Win",IF(L6<0,"Loss","Flat"))) | R6: Sample stop loss
A7: 6 | B7: M15_NIGHT | C7: 2026-02-03 | D7: 2026-02-03 | E7: Long | F7: 1 | G7: 20100 | H7: 20380 | I7: =IF(OR(E7="",G7="",H7=""),"",IF(E7="Short",G7-H7,H7-G7)) | J7: =IF(I7="","",I7*F7*Settings!$B$3) | K7: 120 | L7: =IF(J7="","",J7-K7) | M7: =IF(C7="","",N6) | N7: =IF(L7="","",M7+L7) | O7: =IF(N7="","",MAX(Settings!$B$7,N$2:N7)) | P7: =IF(N7="","",N7-O7) | Q7: =IF(L7="","",IF(L7>0,"Win",IF(L7<0,"Loss","Flat"))) | R7: Sample recovery
A8: 7 | B8: DAY | C8: 2026-02-10 | D8: 2026-02-18 | E8: Long | F8: 1 | G8: 20400 | H8: 21980 | I8: =IF(OR(E8="",G8="",H8=""),"",IF(E8="Short",G8-H8,H8-G8)) | J8: =IF(I8="","",I8*F8*Settings!$B$3) | K8: 120 | L8: =IF(J8="","",J8-K8) | M8: =IF(C8="","",N7) | N8: =IF(L8="","",M8+L8) | O8: =IF(N8="","",MAX(Settings!$B$7,N$2:N8)) | P8: =IF(N8="","",N8-O8) | Q8: =IF(L8="","",IF(L8>0,"Win",IF(L8<0,"Loss","Flat"))) | R8: Sample right tail
A9: 8 | B9: T1O | C9: 2026-02-21 | D9: 2026-02-21 | E9: Short | F9: 2 | G9: 21850 | H9: 21670 | I9: =IF(OR(E9="",G9="",H9=""),"",IF(E9="Short",G9-H9,H9-G9)) | J9: =IF(I9="","",I9*F9*Settings!$B$3) | K9: 240 | L9: =IF(J9="","",J9-K9) | M9: =IF(C9="","",N8) | N9: =IF(L9="","",M9+L9) | O9: =IF(N9="","",MAX(Settings!$B$7,N$2:N9)) | P9: =IF(N9="","",N9-O9) | Q9: =IF(L9="","",IF(L9>0,"Win",IF(L9<0,"Loss","Flat"))) | R9: Sample scaled trade
A10: 9 | B10: M15_NIGHT | C10: 2026-03-05 | D10: 2026-03-05 | E10: Long | F10: 2 | G10: 22000 | H10: 21790 | I10: =IF(OR(E10="",G10="",H10=""),"",IF(E10="Short",G10-H10,H10-G10)) | J10: =IF(I10="","",I10*F10*Settings!$B$3) | K10: 240 | L10: =IF(J10="","",J10-K10) | M10: =IF(C10="","",N9) | N10: =IF(L10="","",M10+L10) | O10: =IF(N10="","",MAX(Settings!$B$7,N$2:N10)) | P10: =IF(N10="","",N10-O10) | Q10: =IF(L10="","",IF(L10>0,"Win",IF(L10<0,"Loss","Flat"))) | R10: Sample cost included
A11: 10 | B11: DAY | C11: 2026-03-12 | D11: 2026-03-17 | E11: Long | F11: 2 | G11: 22100 | H11: 22950 | I11: =IF(OR(E11="",G11="",H11=""),"",IF(E11="Short",G11-H11,H11-G11)) | J11: =IF(I11="","",I11*F11*Settings!$B$3) | K11: 240 | L11: =IF(J11="","",J11-K11) | M11: =IF(C11="","",N10) | N11: =IF(L11="","",M11+L11) | O11: =IF(N11="","",MAX(Settings!$B$7,N$2:N11)) | P11: =IF(N11="","",N11-O11) | Q11: =IF(L11="","",IF(L11>0,"Win",IF(L11<0,"Loss","Flat"))) | R11: Sample trend continuation
A12: 11 | B12: M15_NIGHT | C12: 2026-03-25 | D12: 2026-03-25 | E12: Long | F12: 2 | G12: 23000 | H12: 22820 | I12: =IF(OR(E12="",G12="",H12=""),"",IF(E12="Short",G12-H12,H12-G12)) | J12: =IF(I12="","",I12*F12*Settings!$B$3) | K12: 240 | L12: =IF(J12="","",J12-K12) | M12: =IF(C12="","",N11) | N12: =IF(L12="","",M12+L12) | O12: =IF(N12="","",MAX(Settings!$B$7,N$2:N12)) | P12: =IF(N12="","",N12-O12) | Q12: =IF(L12="","",IF(L12>0,"Win",IF(L12<0,"Loss","Flat"))) | R12: Sample small loss
A13: 12 | B13: T1O | C13: 2026-04-02 | D13: 2026-04-02 | E13: Short | F13: 2 | G13: 22750 | H13: 22480 | I13: =IF(OR(E13="",G13="",H13=""),"",IF(E13="Short",G13-H13,H13-G13)) | J13: =IF(I13="","",I13*F13*Settings!$B$3) | K13: 240 | L13: =IF(J13="","",J13-K13) | M13: =IF(C13="","",N12) | N13: =IF(L13="","",M13+L13) | O13: =IF(N13="","",MAX(Settings!$B$7,N$2:N13)) | P13: =IF(N13="","",N13-O13) | Q13: =IF(L13="","",IF(L13>0,"Win",IF(L13<0,"Loss","Flat"))) | R13: Sample short gain
A14: =IF(C14<>"",A13+1,"") | I14: =IF(OR(E14="",G14="",H14=""),"",IF(E14="Short",G14-H14,H14-G14)) | J14: =IF(I14="","",I14*F14*Settings!$B$3) | L14: =IF(J14="","",J14-K14) | M14: =IF(C14="","",N13) | N14: =IF(L14="","",M14+L14) | O14: =IF(N14="","",MAX(Settings!$B$7,N$2:N14)) | P14: =IF(N14="","",N14-O14) | Q14: =IF(L14="","",IF(L14>0,"Win",IF(L14<0,"Loss","Flat")))
A15: =IF(C15<>"",A14+1,"") | I15: =IF(OR(E15="",G15="",H15=""),"",IF(E15="Short",G15-H15,H15-G15)) | J15: =IF(I15="","",I15*F15*Settings!$B$3) | L15: =IF(J15="","",J15-K15) | M15: =IF(C15="","",N14) | N15: =IF(L15="","",M15+L15) | O15: =IF(N15="","",MAX(Settings!$B$7,N$2:N15)) | P15: =IF(N15="","",N15-O15) | Q15: =IF(L15="","",IF(L15>0,"Win",IF(L15<0,"Loss","Flat")))
A16: =IF(C16<>"",A15+1,"") | I16: =IF(OR(E16="",G16="",H16=""),"",IF(E16="Short",G16-H16,H16-G16)) | J16: =IF(I16="","",I16*F16*Settings!$B$3) | L16: =IF(J16="","",J16-K16) | M16: =IF(C16="","",N15) | N16: =IF(L16="","",M16+L16) | O16: =IF(N16="","",MAX(Settings!$B$7,N$2:N16)) | P16: =IF(N16="","",N16-O16) | Q16: =IF(L16="","",IF(L16>0,"Win",IF(L16<0,"Loss","Flat")))
A17: =IF(C17<>"",A16+1,"") | I17: =IF(OR(E17="",G17="",H17=""),"",IF(E17="Short",G17-H17,H17-G17)) | J17: =IF(I17="","",I17*F17*Settings!$B$3) | L17: =IF(J17="","",J17-K17) | M17: =IF(C17="","",N16) | N17: =IF(L17="","",M17+L17) | O17: =IF(N17="","",MAX(Settings!$B$7,N$2:N17)) | P17: =IF(N17="","",N17-O17) | Q17: =IF(L17="","",IF(L17>0,"Win",IF(L17<0,"Loss","Flat")))
A18: =IF(C18<>"",A17+1,"") | I18: =IF(OR(E18="",G18="",H18=""),"",IF(E18="Short",G18-H18,H18-G18)) | J18: =IF(I18="","",I18*F18*Settings!$B$3) | L18: =IF(J18="","",J18-K18) | M18: =IF(C18="","",N17) | N18: =IF(L18="","",M18+L18) | O18: =IF(N18="","",MAX(Settings!$B$7,N$2:N18)) | P18: =IF(N18="","",N18-O18) | Q18: =IF(L18="","",IF(L18>0,"Win",IF(L18<0,"Loss","Flat")))
A19: =IF(C19<>"",A18+1,"") | I19: =IF(OR(E19="",G19="",H19=""),"",IF(E19="Short",G19-H19,H19-G19)) | J19: =IF(I19="","",I19*F19*Settings!$B$3) | L19: =IF(J19="","",J19-K19) | M19: =IF(C19="","",N18) | N19: =IF(L19="","",M19+L19) | O19: =IF(N19="","",MAX(Settings!$B$7,N$2:N19)) | P19: =IF(N19="","",N19-O19) | Q19: =IF(L19="","",IF(L19>0,"Win",IF(L19<0,"Loss","Flat")))
A20: =IF(C20<>"",A19+1,"") | I20: =IF(OR(E20="",G20="",H20=""),"",IF(E20="Short",G20-H20,H20-G20)) | J20: =IF(I20="","",I20*F20*Settings!$B$3) | L20: =IF(J20="","",J20-K20) | M20: =IF(C20="","",N19) | N20: =IF(L20="","",M20+L20) | O20: =IF(N20="","",MAX(Settings!$B$7,N$2:N20)) | P20: =IF(N20="","",N20-O20) | Q20: =IF(L20="","",IF(L20>0,"Win",IF(L20<0,"Loss","Flat")))
A21: =IF(C21<>"",A20+1,"") | I21: =IF(OR(E21="",G21="",H21=""),"",IF(E21="Short",G21-H21,H21-G21)) | J21: =IF(I21="","",I21*F21*Settings!$B$3) | L21: =IF(J21="","",J21-K21) | M21: =IF(C21="","",N20) | N21: =IF(L21="","",M21+L21) | O21: =IF(N21="","",MAX(Settings!$B$7,N$2:N21)) | P21: =IF(N21="","",N21-O21) | Q21: =IF(L21="","",IF(L21>0,"Win",IF(L21<0,"Loss","Flat")))
A22: =IF(C22<>"",A21+1,"") | I22: =IF(OR(E22="",G22="",H22=""),"",IF(E22="Short",G22-H22,H22-G22)) | J22: =IF(I22="","",I22*F22*Settings!$B$3) | L22: =IF(J22="","",J22-K22) | M22: =IF(C22="","",N21) | N22: =IF(L22="","",M22+L22) | O22: =IF(N22="","",MAX(Settings!$B$7,N$2:N22)) | P22: =IF(N22="","",N22-O22) | Q22: =IF(L22="","",IF(L22>0,"Win",IF(L22<0,"Loss","Flat")))
A23: =IF(C23<>"",A22+1,"") | I23: =IF(OR(E23="",G23="",H23=""),"",IF(E23="Short",G23-H23,H23-G23)) | J23: =IF(I23="","",I23*F23*Settings!$B$3) | L23: =IF(J23="","",J23-K23) | M23: =IF(C23="","",N22) | N23: =IF(L23="","",M23+L23) | O23: =IF(N23="","",MAX(Settings!$B$7,N$2:N23)) | P23: =IF(N23="","",N23-O23) | Q23: =IF(L23="","",IF(L23>0,"Win",IF(L23<0,"Loss","Flat")))
A24: =IF(C24<>"",A23+1,"") | I24: =IF(OR(E24="",G24="",H24=""),"",IF(E24="Short",G24-H24,H24-G24)) | J24: =IF(I24="","",I24*F24*Settings!$B$3) | L24: =IF(J24="","",J24-K24) | M24: =IF(C24="","",N23) | N24: =IF(L24="","",M24+L24) | O24: =IF(N24="","",MAX(Settings!$B$7,N$2:N24)) | P24: =IF(N24="","",N24-O24) | Q24: =IF(L24="","",IF(L24>0,"Win",IF(L24<0,"Loss","Flat")))
A25: =IF(C25<>"",A24+1,"") | I25: =IF(OR(E25="",G25="",H25=""),"",IF(E25="Short",G25-H25,H25-G25)) | J25: =IF(I25="","",I25*F25*Settings!$B$3) | L25: =IF(J25="","",J25-K25) | M25: =IF(C25="","",N24) | N25: =IF(L25="","",M25+L25) | O25: =IF(N25="","",MAX(Settings!$B$7,N$2:N25)) | P25: =IF(N25="","",N25-O25) | Q25: =IF(L25="","",IF(L25>0,"Win",IF(L25<0,"Loss","Flat")))
... A401: =IF(C401<>"",A400+1,"") | I401: =IF(OR(E401="",G401="",H401=""),"",IF(E401="Short",G401-H401,H401-G401)) | J401: =IF(I401="","",I401*F401*Settings!$B$3) | L401: =IF(J401="","",J401-K401) | M401: =IF(C401="","",N400) | N401: =IF(L401="","",M401+L401) | O401: =IF(N401="","",MAX(Settings!$B$7,N$2:N401)) | P401: =IF(N401="","",N401-O401) | Q401: =IF(L401="","",IF(L401>0,"Win",IF(L401<0,"Loss","Flat")))

Sheet Withdrawals
A1: Date | B1: Label | C1: Amount | D1: Status | E1: Count In Total Wealth | F1: Note
A2: 2026-02-28 | B2: Example actual withdrawal | C2: 10000 | D2: Actual | E2: Yes | F2: Money removed from account
A3: 2026-03-31 | B3: Example internal lock | C3: 20000 | D3: Locked | E3: No | F3: Still inside account; do not double count

Sheet Monthly
A1: Month | B1: Net PnL | C1: Trades | D1: Wins | E1: Losses | F1: Win Rate
A2: 2026-01 | B2: =SUMIFS(Trades!L:L,Trades!D:D,">="&DATEVALUE(A2&"-01"),Trades!D:D,"<"&EDATE(DATEVALUE(A2&"-01"),1)) | C2: =COUNTIFS(Trades!D:D,">="&DATEVALUE(A2&"-01"),Trades!D:D,"<"&EDATE(DATEVALUE(A2&"-01"),1)) | D2: =COUNTIFS(Trades!D:D,">="&DATEVALUE(A2&"-01"),Trades!D:D,"<"&EDATE(DATEVALUE(A2&"-01"),1),Trades!Q:Q,"Win") | E2: =COUNTIFS(Trades!D:D,">="&DATEVALUE(A2&"-01"),Trades!D:D,"<"&EDATE(DATEVALUE(A2&"-01"),1),Trades!Q:Q,"Loss") | F2: =IF(C2=0,"",D2/C2)
A3: 2026-02 | B3: =SUMIFS(Trades!L:L,Trades!D:D,">="&DATEVALUE(A3&"-01"),Trades!D:D,"<"&EDATE(DATEVALUE(A3&"-01"),1)) | C3: =COUNTIFS(Trades!D:D,">="&DATEVALUE(A3&"-01"),Trades!D:D,"<"&EDATE(DATEVALUE(A3&"-01"),1)) | D3: =COUNTIFS(Trades!D:D,">="&DATEVALUE(A3&"-01"),Trades!D:D,"<"&EDATE(DATEVALUE(A3&"-01"),1),Trades!Q:Q,"Win") | E3: =COUNTIFS(Trades!D:D,">="&DATEVALUE(A3&"-01"),Trades!D:D,"<"&EDATE(DATEVALUE(A3&"-01"),1),Trades!Q:Q,"Loss") | F3: =IF(C3=0,"",D3/C3)
A4: 2026-03 | B4: =SUMIFS(Trades!L:L,Trades!D:D,">="&DATEVALUE(A4&"-01"),Trades!D:D,"<"&EDATE(DATEVALUE(A4&"-01"),1)) | C4: =COUNTIFS(Trades!D:D,">="&DATEVALUE(A4&"-01"),Trades!D:D,"<"&EDATE(DATEVALUE(A4&"-01"),1)) | D4: =COUNTIFS(Trades!D:D,">="&DATEVALUE(A4&"-01"),Trades!D:D,"<"&EDATE(DATEVALUE(A4&"-01"),1),Trades!Q:Q,"Win") | E4: =COUNTIFS(Trades!D:D,">="&DATEVALUE(A4&"-01"),Trades!D:D,"<"&EDATE(DATEVALUE(A4&"-01"),1),Trades!Q:Q,"Loss") | F4: =IF(C4=0,"",D4/C4)
A5: 2026-04 | B5: =SUMIFS(Trades!L:L,Trades!D:D,">="&DATEVALUE(A5&"-01"),Trades!D:D,"<"&EDATE(DATEVALUE(A5&"-01"),1)) | C5: =COUNTIFS(Trades!D:D,">="&DATEVALUE(A5&"-01"),Trades!D:D,"<"&EDATE(DATEVALUE(A5&"-01"),1)) | D5: =COUNTIFS(Trades!D:D,">="&DATEVALUE(A5&"-01"),Trades!D:D,"<"&EDATE(DATEVALUE(A5&"-01"),1),Trades!Q:Q,"Win") | E5: =COUNTIFS(Trades!D:D,">="&DATEVALUE(A5&"-01"),Trades!D:D,"<"&EDATE(DATEVALUE(A5&"-01"),1),Trades!Q:Q,"Loss") | F5: =IF(C5=0,"",D5/C5)
A6: 2026-05 | B6: =SUMIFS(Trades!L:L,Trades!D:D,">="&DATEVALUE(A6&"-01"),Trades!D:D,"<"&EDATE(DATEVALUE(A6&"-01"),1)) | C6: =COUNTIFS(Trades!D:D,">="&DATEVALUE(A6&"-01"),Trades!D:D,"<"&EDATE(DATEVALUE(A6&"-01"),1)) | D6: =COUNTIFS(Trades!D:D,">="&DATEVALUE(A6&"-01"),Trades!D:D,"<"&EDATE(DATEVALUE(A6&"-01"),1),Trades!Q:Q,"Win") | E6: =COUNTIFS(Trades!D:D,">="&DATEVALUE(A6&"-01"),Trades!D:D,"<"&EDATE(DATEVALUE(A6&"-01"),1),Trades!Q:Q,"Loss") | F6: =IF(C6=0,"",D6/C6)
A7: 2026-06 | B7: =SUMIFS(Trades!L:L,Trades!D:D,">="&DATEVALUE(A7&"-01"),Trades!D:D,"<"&EDATE(DATEVALUE(A7&"-01"),1)) | C7: =COUNTIFS(Trades!D:D,">="&DATEVALUE(A7&"-01"),Trades!D:D,"<"&EDATE(DATEVALUE(A7&"-01"),1)) | D7: =COUNTIFS(Trades!D:D,">="&DATEVALUE(A7&"-01"),Trades!D:D,"<"&EDATE(DATEVALUE(A7&"-01"),1),Trades!Q:Q,"Win") | E7: =COUNTIFS(Trades!D:D,">="&DATEVALUE(A7&"-01"),Trades!D:D,"<"&EDATE(DATEVALUE(A7&"-01"),1),Trades!Q:Q,"Loss") | F7: =IF(C7=0,"",D7/C7)

Sheet Notes
A1: Topic | B1: Note
A2: Purpose | B2: This file is a capital management and research template, not a trading signal system.
A3: Withdrawal logic | B3: Actual withdrawals count into total wealth. Locked or pending records do not double count.
A4: Risk | B4: Always include fees, tax, slippage, margin changes, and execution errors.
A5: Open source boundary | B5: Do not publish live strategy rules, account size, broker statements, or full private trade logs.
